{"title":"[MyLatinaTeen] E1315 Jackie","uid":7158432,"size":255695211,"categoryP":"porn","categoryS":"movie_clips","magnet":"?xt=urn:btih:115d8e2ee1b5ff53cf213a70932e39a746a50e6c&amp;dn=%5BMyLatinaTeen%5D+E1315+Jackie&amp;tr=udp%3A%2F%2Ftracker.openbittorrent.com%3A80&amp;tr=udp%3A%2F%2Fopen.demonii.com%3A1337&amp;tr=udp%3A%2F%2Ftracker.coppersurfer.tk%3A6969&amp;tr=udp%3A%2F%2Fexodus.desync.com%3A6969","seeders":0,"leechers":0,"uploader":"chkm8te","files":1,"time":1333527528,"description":"Screens: &lt;a href=&quot;\nhttp://4ufrom.me/viewer.php?file=929qryf8apz2gswwudvs.jpg&quot; rel=&quot;nofollow&quot; target=&quot;_NEW&quot;&gt;\nhttp://4ufrom.me/viewer.php?file=929qryf8apz2gswwudvs.jpg&lt;/a&gt;","torrent":{"xt":"urn:btih:115d8e2ee1b5ff53cf213a70932e39a746a50e6c","amp;dn":"%5BMyLatinaTeen%5D+E1315+Jackie","amp;tr":["udp%3A%2F%2Ftracker.openbittorrent.com%3A80","udp%3A%2F%2Fopen.demonii.com%3A1337","udp%3A%2F%2Ftracker.coppersurfer.tk%3A6969","udp%3A%2F%2Fexodus.desync.com%3A6969"],"infoHash":"115d8e2ee1b5ff53cf213a70932e39a746a50e6c","infoHashBuffer":{"type":"Buffer","data":[17,93,142,46,225,181,255,83,207,33,58,112,147,46,57,167,70,165,14,108]},"announce":[],"urlList":[]}}