{"title":"The.Catalina.S01E02.HDTV.XviD-AFG","uid":7333193,"size":338039118,"categoryP":"video","categoryS":"tv_shows","magnet":"?xt=urn:btih:1c20d5ea8e072b59fb097e88a296bd0baee7cf97&amp;dn=The.Catalina.S01E02.HDTV.XviD-AFG&amp;tr=udp%3A%2F%2Ftracker.openbittorrent.com%3A80&amp;tr=udp%3A%2F%2Fopen.demonii.com%3A1337&amp;tr=udp%3A%2F%2Ftracker.coppersurfer.tk%3A6969&amp;tr=udp%3A%2F%2Fexodus.desync.com%3A6969","seeders":0,"leechers":1,"uploader":"TvTeam","files":4,"time":1338981002,"description":".  TD Sign UP is open. so you better hurry up ;) ENJOYYY!!!!     (^_~)  \n  &lt;a href=&quot;\nhttp://www.torrentday.com&quot; rel=&quot;nofollow&quot; target=&quot;_NEW&quot;&gt;\nhttp://www.torrentday.com&lt;/a&gt;\n\n\nTo Avoid Fakes, ALWAYS Check That The Torrent Was Added By: TvTeam.\n\n\n               www . TorrentDay . Com \n(((((((((((((= Enjoy No RAR releases =))))))))))))))))))))\n\n...................................NFO:....................................\n\nEnjoy our Fast Upload.\nFor more info about this release, open .NFO file with notepad :)","torrent":{"xt":"urn:btih:1c20d5ea8e072b59fb097e88a296bd0baee7cf97","amp;dn":"The.Catalina.S01E02.HDTV.XviD-AFG","amp;tr":["udp%3A%2F%2Ftracker.openbittorrent.com%3A80","udp%3A%2F%2Fopen.demonii.com%3A1337","udp%3A%2F%2Ftracker.coppersurfer.tk%3A6969","udp%3A%2F%2Fexodus.desync.com%3A6969"],"infoHash":"1c20d5ea8e072b59fb097e88a296bd0baee7cf97","infoHashBuffer":{"type":"Buffer","data":[28,32,213,234,142,7,43,89,251,9,126,136,162,150,189,11,174,231,207,151]},"announce":[],"urlList":[]}}