{"title":"digimon 221 - the crest of kindess [sasuke].avi","uid":7150925,"size":170904534,"categoryP":"video","categoryS":"tv_shows","magnet":"?xt=urn:btih:3bffa593cb2c91789ca5b7daf8b26847845d3e62&amp;dn=digimon+221+-+the+crest+of+kindess+%5Bsasuke%5D.avi&amp;tr=udp%3A%2F%2Ftracker.openbittorrent.com%3A80&amp;tr=udp%3A%2F%2Fopen.demonii.com%3A1337&amp;tr=udp%3A%2F%2Ftracker.coppersurfer.tk%3A6969&amp;tr=udp%3A%2F%2Fexodus.desync.com%3A6969","seeders":0,"leechers":0,"uploader":"hotwire138","files":1,"time":1333309102,"description":"for rest of episodes check my profile.","torrent":{"xt":"urn:btih:3bffa593cb2c91789ca5b7daf8b26847845d3e62","amp;dn":"digimon+221+-+the+crest+of+kindess+%5Bsasuke%5D.avi","amp;tr":["udp%3A%2F%2Ftracker.openbittorrent.com%3A80","udp%3A%2F%2Fopen.demonii.com%3A1337","udp%3A%2F%2Ftracker.coppersurfer.tk%3A6969","udp%3A%2F%2Fexodus.desync.com%3A6969"],"infoHash":"3bffa593cb2c91789ca5b7daf8b26847845d3e62","infoHashBuffer":{"type":"Buffer","data":[59,255,165,147,203,44,145,120,156,165,183,218,248,178,104,71,132,93,62,98]},"announce":[],"urlList":[]}}