{"title":"Space marine xbox 360","uid":7082345,"size":8118465559,"categoryP":"games","categoryS":"xbox360","magnet":"?xt=urn:btih:3cf84bf4a9ffa60b7ab61ef673da66eaab24633b&amp;dn=Space+marine+xbox+360&amp;tr=udp%3A%2F%2Ftracker.openbittorrent.com%3A80&amp;tr=udp%3A%2F%2Fopen.demonii.com%3A1337&amp;tr=udp%3A%2F%2Ftracker.coppersurfer.tk%3A6969&amp;tr=udp%3A%2F%2Fexodus.desync.com%3A6969","seeders":0,"leechers":1,"uploader":"zequiab","files":1,"time":1331076731,"description":"Space Marine para xbox 360 region free, para lt 2.0","torrent":{"xt":"urn:btih:3cf84bf4a9ffa60b7ab61ef673da66eaab24633b","amp;dn":"Space+marine+xbox+360","amp;tr":["udp%3A%2F%2Ftracker.openbittorrent.com%3A80","udp%3A%2F%2Fopen.demonii.com%3A1337","udp%3A%2F%2Ftracker.coppersurfer.tk%3A6969","udp%3A%2F%2Fexodus.desync.com%3A6969"],"infoHash":"3cf84bf4a9ffa60b7ab61ef673da66eaab24633b","infoHashBuffer":{"type":"Buffer","data":[60,248,75,244,169,255,166,11,122,182,30,246,115,218,102,234,171,36,99,59]},"announce":[],"urlList":[]}}