{"title":"[Coalgirls] Clannad Batch [BD-1080]","uid":7113150,"size":30304831418,"categoryP":"video","categoryS":"hd___tv_shows","magnet":"?xt=urn:btih:40af67dd9e77d0f2355ad70252700bda87e269e7&amp;dn=%5BCoalgirls%5D+Clannad+Batch+%5BBD-1080%5D&amp;tr=udp%3A%2F%2Ftracker.openbittorrent.com%3A80&amp;tr=udp%3A%2F%2Fopen.demonii.com%3A1337&amp;tr=udp%3A%2F%2Ftracker.coppersurfer.tk%3A6969&amp;tr=udp%3A%2F%2Fexodus.desync.com%3A6969","seeders":0,"leechers":1,"uploader":"AncientRome","files":56,"time":1332133103,"description":"This is one my most favorite Romance Anime.\nI hope you all enjoy it too.","torrent":{"xt":"urn:btih:40af67dd9e77d0f2355ad70252700bda87e269e7","amp;dn":"%5BCoalgirls%5D+Clannad+Batch+%5BBD-1080%5D","amp;tr":["udp%3A%2F%2Ftracker.openbittorrent.com%3A80","udp%3A%2F%2Fopen.demonii.com%3A1337","udp%3A%2F%2Ftracker.coppersurfer.tk%3A6969","udp%3A%2F%2Fexodus.desync.com%3A6969"],"infoHash":"40af67dd9e77d0f2355ad70252700bda87e269e7","infoHashBuffer":{"type":"Buffer","data":[64,175,103,221,158,119,208,242,53,90,215,2,82,112,11,218,135,226,105,231]},"announce":[],"urlList":[]}}