{"title":"8thStreetLatinas - Eve Evans","uid":7047397,"size":462426561,"categoryP":"porn","categoryS":"other","magnet":"?xt=urn:btih:46f46313a1d6f84de21c0e604d91a5accbb1abcc&amp;dn=8thStreetLatinas+-+Eve+Evans&amp;tr=udp%3A%2F%2Ftracker.openbittorrent.com%3A80&amp;tr=udp%3A%2F%2Fopen.demonii.com%3A1337&amp;tr=udp%3A%2F%2Ftracker.coppersurfer.tk%3A6969&amp;tr=udp%3A%2F%2Fexodus.desync.com%3A6969","seeders":0,"leechers":1,"uploader":"perfectblue","files":-1,"time":1329793926,"description":"SCREENSHOTS\n\n\nMORE\n &lt;a href=&quot;\nhttp://perfectblue.xlogs.org/archives/8thstreetlatinas-eve-evans-473/&quot; rel=&quot;nofollow&quot; target=&quot;_NEW&quot;&gt;\nhttp://perfectblue.xlogs.org/archives/8thstreetlatinas-eve-evans-473/&lt;/a&gt;","torrent":{"xt":"urn:btih:46f46313a1d6f84de21c0e604d91a5accbb1abcc","amp;dn":"8thStreetLatinas+-+Eve+Evans","amp;tr":["udp%3A%2F%2Ftracker.openbittorrent.com%3A80","udp%3A%2F%2Fopen.demonii.com%3A1337","udp%3A%2F%2Ftracker.coppersurfer.tk%3A6969","udp%3A%2F%2Fexodus.desync.com%3A6969"],"infoHash":"46f46313a1d6f84de21c0e604d91a5accbb1abcc","infoHashBuffer":{"type":"Buffer","data":[70,244,99,19,161,214,248,77,226,28,14,96,77,145,165,172,203,177,171,204]},"announce":[],"urlList":[]}}