{"title":"Star Wars Episodes I-VI + ENG subs","uid":7072994,"size":8817887701,"categoryP":"video","categoryS":"movies","magnet":"?xt=urn:btih:57657e96813481c892385e138403cff119d15543&amp;dn=Star+Wars+Episodes+I-VI+%2B+ENG+subs&amp;tr=udp%3A%2F%2Ftracker.openbittorrent.com%3A80&amp;tr=udp%3A%2F%2Fopen.demonii.com%3A1337&amp;tr=udp%3A%2F%2Ftracker.coppersurfer.tk%3A6969&amp;tr=udp%3A%2F%2Fexodus.desync.com%3A6969","seeders":0,"leechers":1,"uploader":"felixanel","files":12,"time":1330739336,"description":"In the torrent:\n\n720p BRRip Episodes I, II &amp; III\n720p Episodes IV, V &amp; VI\n\nEnglish subtitles\n\nEnjoy!","torrent":{"xt":"urn:btih:57657e96813481c892385e138403cff119d15543","amp;dn":"Star+Wars+Episodes+I-VI+%2B+ENG+subs","amp;tr":["udp%3A%2F%2Ftracker.openbittorrent.com%3A80","udp%3A%2F%2Fopen.demonii.com%3A1337","udp%3A%2F%2Ftracker.coppersurfer.tk%3A6969","udp%3A%2F%2Fexodus.desync.com%3A6969"],"infoHash":"57657e96813481c892385e138403cff119d15543","infoHashBuffer":{"type":"Buffer","data":[87,101,126,150,129,52,129,200,146,56,94,19,132,3,207,241,25,209,85,67]},"announce":[],"urlList":[]}}