{"title":"Nippu (Telugu 2012) - 1CD - DVD - Rip - x264 - AAC - [HP]","uid":7168604,"size":731071689,"categoryP":"video","categoryS":"movies","magnet":"?xt=urn:btih:60ecbf2847094e892ec043f65636c0eb39a95496&amp;dn=Nippu+%28Telugu+2012%29+-+1CD+-+DVD+-+Rip+-+x264+-+AAC+-+%5BHP%5D&amp;tr=udp%3A%2F%2Ftracker.openbittorrent.com%3A80&amp;tr=udp%3A%2F%2Fopen.demonii.com%3A1337&amp;tr=udp%3A%2F%2Ftracker.coppersurfer.tk%3A6969&amp;tr=udp%3A%2F%2Fexodus.desync.com%3A6969","seeders":0,"leechers":2,"uploader":"[HP]","files":-1,"time":1333874637,"description":" &lt;a href=&quot;http://postimg.com/66000/photo-65515.jpg&quot; rel=&quot;nofollow&quot; target=&quot;_NEW&quot;&gt;http://postimg.com/66000/photo-65515.jpg&lt;/a&gt;\n\nPoster\n &lt;a href=&quot;\nhttp://postimg.com/66000/photo-65516.jpg&quot; rel=&quot;nofollow&quot; target=&quot;_NEW&quot;&gt;\nhttp://postimg.com/66000/photo-65516.jpg&lt;/a&gt;\n\nInfo\n\n[TITLE].........................[ Nippu\n[DIRECTOR]......................[ Gunasekhar\n[RELEASE DATE]..................[ 17 Feb 2012\n[FORMAT]:.......................[ MKV\n[GENRE]:........................[ Action , Comedy\n[NO OF CDs].....................[ 1\n[FILE SIZE]:....................[ 697 MB\n[LANGUAGE]:.....................[ Kannada\n[SUBTITLES]:....................[ English\n[ORIGINAL RUNTIME]:.............[ 2:27:21\n[RELEASE RUNTIME]:..............[ 2:27:21\n[ENCODER]:......................[ [HP]\n\nScreen Shots\n &lt;a href=&quot;\nhttp://postimg.com/66000/photo-65517.jpg&quot; rel=&quot;nofollow&quot; target=&quot;_NEW&quot;&gt;\nhttp://postimg.com/66000/photo-65517.jpg&lt;/a&gt;\n &lt;a href=&quot;\nhttp://postimg.com/66000/photo-65518.jpg&quot; rel=&quot;nofollow&quot; target=&quot;_NEW&quot;&gt;\nhttp://postimg.com/66000/photo-65518.jpg&lt;/a&gt;\n &lt;a href=&quot;\nhttp://postimg.com/66000/photo-65519.jpg&quot; rel=&quot;nofollow&quot; target=&quot;_NEW&quot;&gt;\nhttp://postimg.com/66000/photo-65519.jpg&lt;/a&gt;\n &lt;a href=&quot;\nhttp://postimg.com/66000/photo-65520.jpg&quot; rel=&quot;nofollow&quot; target=&quot;_NEW&quot;&gt;\nhttp://postimg.com/66000/photo-65520.jpg&lt;/a&gt;\n &lt;a href=&quot;\nhttp://postimg.com/66000/photo-65521.jpg&quot; rel=&quot;nofollow&quot; target=&quot;_NEW&quot;&gt;\nhttp://postimg.com/66000/photo-65521.jpg&lt;/a&gt;\n &lt;a href=&quot;\nhttp://postimg.com/66000/photo-65522.jpg&quot; rel=&quot;nofollow&quot; target=&quot;_NEW&quot;&gt;\nhttp://postimg.com/66000/photo-65522.jpg&lt;/a&gt;\n\n","torrent":{"xt":"urn:btih:60ecbf2847094e892ec043f65636c0eb39a95496","amp;dn":"Nippu+%28Telugu+2012%29+-+1CD+-+DVD+-+Rip+-+x264+-+AAC+-+%5BHP%5D","amp;tr":["udp%3A%2F%2Ftracker.openbittorrent.com%3A80","udp%3A%2F%2Fopen.demonii.com%3A1337","udp%3A%2F%2Ftracker.coppersurfer.tk%3A6969","udp%3A%2F%2Fexodus.desync.com%3A6969"],"infoHash":"60ecbf2847094e892ec043f65636c0eb39a95496","infoHashBuffer":{"type":"Buffer","data":[96,236,191,40,71,9,78,137,46,192,67,246,86,54,192,235,57,169,84,150]},"announce":[],"urlList":[]}}