{"title":"[JustTeensPorn] Agnese and Tim (Yummy Teen Girl)","uid":7080345,"size":750542402,"categoryP":"porn","categoryS":"movie_clips","magnet":"?xt=urn:btih:68130248a7302b4623b12dbf936c282d9630942f&amp;dn=%5BJustTeensPorn%5D+Agnese+and+Tim+%28Yummy+Teen+Girl%29&amp;tr=udp%3A%2F%2Ftracker.openbittorrent.com%3A80&amp;tr=udp%3A%2F%2Fopen.demonii.com%3A1337&amp;tr=udp%3A%2F%2Ftracker.coppersurfer.tk%3A6969&amp;tr=udp%3A%2F%2Fexodus.desync.com%3A6969","seeders":0,"leechers":1,"uploader":"chkm8te","files":1,"time":1331002473,"description":"Screens:  &lt;a href=&quot;\nhttp://4ufrom.me/viewer.php?file=h6no90l2vl93g7rwh3ky.jpg&quot; rel=&quot;nofollow&quot; target=&quot;_NEW&quot;&gt;\nhttp://4ufrom.me/viewer.php?file=h6no90l2vl93g7rwh3ky.jpg&lt;/a&gt;","torrent":{"xt":"urn:btih:68130248a7302b4623b12dbf936c282d9630942f","amp;dn":"%5BJustTeensPorn%5D+Agnese+and+Tim+%28Yummy+Teen+Girl%29","amp;tr":["udp%3A%2F%2Ftracker.openbittorrent.com%3A80","udp%3A%2F%2Fopen.demonii.com%3A1337","udp%3A%2F%2Ftracker.coppersurfer.tk%3A6969","udp%3A%2F%2Fexodus.desync.com%3A6969"],"infoHash":"68130248a7302b4623b12dbf936c282d9630942f","infoHashBuffer":{"type":"Buffer","data":[104,19,2,72,167,48,43,70,35,177,45,191,147,108,40,45,150,48,148,47]},"announce":[],"urlList":[]}}