{"title":"Hawaii five-01x02microhdtv_castellano","uid":7061110,"size":556897544,"categoryP":"video","categoryS":"movie_clips","magnet":"?xt=urn:btih:71a7202231be29d10db4169f80537e6b56aa458e&amp;dn=Hawaii+five-01x02microhdtv_castellano&amp;tr=udp%3A%2F%2Ftracker.openbittorrent.com%3A80&amp;tr=udp%3A%2F%2Fopen.demonii.com%3A1337&amp;tr=udp%3A%2F%2Ftracker.coppersurfer.tk%3A6969&amp;tr=udp%3A%2F%2Fexodus.desync.com%3A6969","seeders":0,"leechers":0,"uploader":"Anonymous32","files":1,"time":1330347920,"description":"serie policiaca en hawaii","torrent":{"xt":"urn:btih:71a7202231be29d10db4169f80537e6b56aa458e","amp;dn":"Hawaii+five-01x02microhdtv_castellano","amp;tr":["udp%3A%2F%2Ftracker.openbittorrent.com%3A80","udp%3A%2F%2Fopen.demonii.com%3A1337","udp%3A%2F%2Ftracker.coppersurfer.tk%3A6969","udp%3A%2F%2Fexodus.desync.com%3A6969"],"infoHash":"71a7202231be29d10db4169f80537e6b56aa458e","infoHashBuffer":{"type":"Buffer","data":[113,167,32,34,49,190,41,209,13,180,22,159,128,83,126,107,86,170,69,142]},"announce":[],"urlList":[]}}