{"title":"2 - Some penetrations are good - Jack Harrer &amp; Dario Dolce.m","uid":7089750,"size":794081120,"categoryP":"porn","categoryS":"hd___movies","magnet":"?xt=urn:btih:723022dac2c0b2e34f511adaf2bdacbfcd810084&amp;dn=2+-+Some+penetrations+are+good+-+Jack+Harrer+%26amp%3B+Dario+Dolce.m&amp;tr=udp%3A%2F%2Ftracker.openbittorrent.com%3A80&amp;tr=udp%3A%2F%2Fopen.demonii.com%3A1337&amp;tr=udp%3A%2F%2Ftracker.coppersurfer.tk%3A6969&amp;tr=udp%3A%2F%2Fexodus.desync.com%3A6969","seeders":0,"leechers":1,"uploader":"dodgerblue","files":1,"time":1331325842,"description":" &lt;a href=&quot;http://i&quot; rel=&quot;nofollow&quot; target=&quot;_NEW&quot;&gt;http://i&lt;/a&gt; mgchili.com/show/5727/5727996_2___some_penetration.png","torrent":{"xt":"urn:btih:723022dac2c0b2e34f511adaf2bdacbfcd810084","amp;dn":"2+-+Some+penetrations+are+good+-+Jack+Harrer+%26amp%3B+Dario+Dolce.m","amp;tr":["udp%3A%2F%2Ftracker.openbittorrent.com%3A80","udp%3A%2F%2Fopen.demonii.com%3A1337","udp%3A%2F%2Ftracker.coppersurfer.tk%3A6969","udp%3A%2F%2Fexodus.desync.com%3A6969"],"infoHash":"723022dac2c0b2e34f511adaf2bdacbfcd810084","infoHashBuffer":{"type":"Buffer","data":[114,48,34,218,194,192,178,227,79,81,26,218,242,189,172,191,205,129,0,132]},"announce":[],"urlList":[]}}