{"title":"Caris Val &amp; Adrian","uid":7041699,"size":319769085,"categoryP":"porn","categoryS":"movie_clips","magnet":"?xt=urn:btih:78beea7299b7e834c350a94700832ed841649574&amp;dn=Caris+Val+%26amp%3B+Adrian&amp;tr=udp%3A%2F%2Ftracker.openbittorrent.com%3A80&amp;tr=udp%3A%2F%2Fopen.demonii.com%3A1337&amp;tr=udp%3A%2F%2Ftracker.coppersurfer.tk%3A6969&amp;tr=udp%3A%2F%2Fexodus.desync.com%3A6969","seeders":0,"leechers":0,"uploader":"green.rooster","files":9,"time":1329572309,"description":"Caris Val &amp; Adrian - This bubbly brunette decides to sunbake naked in the woods, until she gets sprung by a horny older couple looking for a good SHAG! See this cutie pie get it on with them and get smothered by a massive set of mammories!\n\nVital Statistics Her - Age - 26-30, Build - Slim, Hair Color - Black\nVital Statistics Her - Age - 31-35, Build - BBW, Hair Color - Red\nVital Statistics Him - Age - 36-40, Build - Slim, Hair Color - Shaved\n\nCountry Of Origin - DE\n\nMovie Category - Group\n\nMovie Length - 28:18 min\n\n","torrent":{"xt":"urn:btih:78beea7299b7e834c350a94700832ed841649574","amp;dn":"Caris+Val+%26amp%3B+Adrian","amp;tr":["udp%3A%2F%2Ftracker.openbittorrent.com%3A80","udp%3A%2F%2Fopen.demonii.com%3A1337","udp%3A%2F%2Ftracker.coppersurfer.tk%3A6969","udp%3A%2F%2Fexodus.desync.com%3A6969"],"infoHash":"78beea7299b7e834c350a94700832ed841649574","infoHashBuffer":{"type":"Buffer","data":[120,190,234,114,153,183,232,52,195,80,169,71,0,131,46,216,65,100,149,116]},"announce":[],"urlList":[]}}