{"title":"50 Amazing Cityscapes HD Wallpapers 1366 X 768 [Set 4]","uid":7034535,"size":38398791,"categoryP":"other","categoryS":"pictures","magnet":"?xt=urn:btih:7af90f1e2e624a6f471cb56f7cbc3ac2a6fcce90&amp;dn=50+Amazing+Cityscapes+HD+Wallpapers+1366+X+768+%5BSet+4%5D&amp;tr=udp%3A%2F%2Ftracker.openbittorrent.com%3A80&amp;tr=udp%3A%2F%2Fopen.demonii.com%3A1337&amp;tr=udp%3A%2F%2Ftracker.coppersurfer.tk%3A6969&amp;tr=udp%3A%2F%2Fexodus.desync.com%3A6969","seeders":0,"leechers":1,"uploader":"nico1899","files":-1,"time":1329333712,"description":"50 Amazing Cityscapes HD Wallpapers 1366 X 768 [Set 4]\n\n50 JPG | 1366 X 768 Px | 36.6 Mb","torrent":{"xt":"urn:btih:7af90f1e2e624a6f471cb56f7cbc3ac2a6fcce90","amp;dn":"50+Amazing+Cityscapes+HD+Wallpapers+1366+X+768+%5BSet+4%5D","amp;tr":["udp%3A%2F%2Ftracker.openbittorrent.com%3A80","udp%3A%2F%2Fopen.demonii.com%3A1337","udp%3A%2F%2Ftracker.coppersurfer.tk%3A6969","udp%3A%2F%2Fexodus.desync.com%3A6969"],"infoHash":"7af90f1e2e624a6f471cb56f7cbc3ac2a6fcce90","infoHashBuffer":{"type":"Buffer","data":[122,249,15,30,46,98,74,111,71,28,181,111,124,188,58,194,166,252,206,144]},"announce":[],"urlList":[]}}