{"title":"Cougars Crave Young Kittens 9 (DvdRip)","uid":7180465,"size":1462294528,"categoryP":"porn","categoryS":"movies","magnet":"?xt=urn:btih:7b87f045bc2a0e55c076a6b3e539e52cf403dbfd&amp;dn=Cougars+Crave+Young+Kittens+9+%28DvdRip%29&amp;tr=udp%3A%2F%2Ftracker.openbittorrent.com%3A80&amp;tr=udp%3A%2F%2Fopen.demonii.com%3A1337&amp;tr=udp%3A%2F%2Ftracker.coppersurfer.tk%3A6969&amp;tr=udp%3A%2F%2Fexodus.desync.com%3A6969","seeders":0,"leechers":2,"uploader":"FluxXxu","files":2,"time":1334248280,"description":"Cougars Crave Young Kittens 9 (DvdRip)\n\nMagdalene St. Michaels, Joclyn Stone, Totally Tabitha, Presley Hart, Esperanza Diaz, Cherie DeVille, Risi Simms, Chloe Lynn\n\nCherie was so fed p with her husband's neglect that she decided to seduce her step daughter Presley so she could get off and get even! Magdalene's pussy got soaking wet when she saw Chloe try on a dress, so she helped her out of her panties ... Full Descriptionso licked her sweet pussy until she came! When Tabitha found her stepdaughter Esperanze sleeping in her bed she couldn't resit showing her tongue in her pussy and caressing her sweet bubble butt! Risi attended a time-share seminar to receive a free gift, but she never expected it to have hot lesbian sex with Joclyn, the curvaceous salesperson!\n\nCougars Teach Teens How To Orgasm!\n\nCherie was so fed p with her husband's neglect that she decided to seduce her step daughter Presley so she could get off and get even! Magdalene's pussy got soaking wet when she saw Chloe try on a dress, so she helped her out of her panties so licked her sweet pussy until she came! When Tabitha found her stepdaughter Esperanze laying in her bed she couldn't resit showing her tongue in her pussy and caressing her sweet bubble butt! Risi attended a time-share seminar to receive a free gift, but she never expected it to have hot lesbian sex with Joclyn, the curvaceous salesperson!\n\nTags: Hardcore, sex, xXx\n\nScreens:\n &lt;a href=&quot;\nhttp://imgunix.com/viewer.php?file=red4jhqf.jpg&quot; rel=&quot;nofollow&quot; target=&quot;_NEW&quot;&gt;\nhttp://imgunix.com/viewer.php?file=red4jhqf.jpg&lt;/a&gt;\n &lt;a href=&quot;\nhttp://imgunix.com/viewer.php?file=xa4t0ecq.jpg&quot; rel=&quot;nofollow&quot; target=&quot;_NEW&quot;&gt;\nhttp://imgunix.com/viewer.php?file=xa4t0ecq.jpg&lt;/a&gt;\n &lt;a href=&quot;\nhttp://imgunix.com/viewer.php?file=w66bpnge.jpg&quot; rel=&quot;nofollow&quot; target=&quot;_NEW&quot;&gt;\nhttp://imgunix.com/viewer.php?file=w66bpnge.jpg&lt;/a&gt;","torrent":{"xt":"urn:btih:7b87f045bc2a0e55c076a6b3e539e52cf403dbfd","amp;dn":"Cougars+Crave+Young+Kittens+9+%28DvdRip%29","amp;tr":["udp%3A%2F%2Ftracker.openbittorrent.com%3A80","udp%3A%2F%2Fopen.demonii.com%3A1337","udp%3A%2F%2Ftracker.coppersurfer.tk%3A6969","udp%3A%2F%2Fexodus.desync.com%3A6969"],"infoHash":"7b87f045bc2a0e55c076a6b3e539e52cf403dbfd","infoHashBuffer":{"type":"Buffer","data":[123,135,240,69,188,42,14,85,192,118,166,179,229,57,229,44,244,3,219,253]},"announce":[],"urlList":[]}}