{"title":"Treasure Island dvd2(dvd5)(Nl subs) RETAIL TBS B-SAM","uid":7148192,"size":4299025543,"categoryP":"video","categoryS":"movies_dvdr","magnet":"?xt=urn:btih:82fd36470e50c050f8b7365ddc25cd1084fe11d6&amp;dn=Treasure+Island+dvd2%28dvd5%29%28Nl+subs%29+RETAIL+TBS+B-SAM&amp;tr=udp%3A%2F%2Ftracker.openbittorrent.com%3A80&amp;tr=udp%3A%2F%2Fopen.demonii.com%3A1337&amp;tr=udp%3A%2F%2Ftracker.coppersurfer.tk%3A6969&amp;tr=udp%3A%2F%2Fexodus.desync.com%3A6969","seeders":0,"leechers":1,"uploader":"Sammynet","files":-1,"time":1333206804,"description":"Treasure Island (2012) DVD 2\n\nNederlands\nDe jonge Jim Hawkins is de enige die met een zeilschip een legendarisch eiland,\ndat bekend staat om zijn verborgen schatten, kan bereiken.\nMaar aan boord van het schip bevindt zich ook de mysterieuze kok John Silver,\nwiens ware motivatie voor de reis er voor zorgt dat Jim twijfels krijgt tegenover de gehele bemanning.\n\nEnglish\nThis two part drama follows the story of Jim Hawkins,\nwho's unexpectedly drawn into the world of piracy when he discovers Flint's treasure map.\nHowever, Long John Silver will stop at nothing to get hold of the gold for himself.\nAs they set sail for Treasure Island, Jim embarks on an action adventure that will change his life forever.\n\nSpotinformatie\n\nSource............: Retail\nFormaat...........: DVD5\nVideo.............: PAL\nAudio.............: English DD5.1\nGenre.............: Avontuur\nSubs..............: Dutch\nMenu..............: Yes\njaar uitgave......: 2012\nCover &amp; label.....: Yes\nAudio.............: English &amp; spoken\nSpeelduur.........: 180 minuten\nminiserie.........: 2 DVD's\n &lt;a href=&quot;\nhttp://www.imdb.com/title/tt1820723/&quot; rel=&quot;nofollow&quot; target=&quot;_NEW&quot;&gt;\nhttp://www.imdb.com/title/tt1820723/&lt;/a&gt;\n &lt;a href=&quot;\nhttp://www.moviemeter.nl/film/81340&quot; rel=&quot;nofollow&quot; target=&quot;_NEW&quot;&gt;\nhttp://www.moviemeter.nl/film/81340&lt;/a&gt;","torrent":{"xt":"urn:btih:82fd36470e50c050f8b7365ddc25cd1084fe11d6","amp;dn":"Treasure+Island+dvd2%28dvd5%29%28Nl+subs%29+RETAIL+TBS+B-SAM","amp;tr":["udp%3A%2F%2Ftracker.openbittorrent.com%3A80","udp%3A%2F%2Fopen.demonii.com%3A1337","udp%3A%2F%2Ftracker.coppersurfer.tk%3A6969","udp%3A%2F%2Fexodus.desync.com%3A6969"],"infoHash":"82fd36470e50c050f8b7365ddc25cd1084fe11d6","infoHashBuffer":{"type":"Buffer","data":[130,253,54,71,14,80,192,80,248,183,54,93,220,37,205,16,132,254,17,214]},"announce":[],"urlList":[]}}