{"title":"Rest Stop (2006)(IPOD)","uid":7074114,"size":339253317,"categoryP":"video","categoryS":"handheld","magnet":"?xt=urn:btih:9aa8a5a8ed8e6c75244d93e9a84af5f8f41971e4&amp;dn=Rest+Stop+%282006%29%28IPOD%29&amp;tr=udp%3A%2F%2Ftracker.openbittorrent.com%3A80&amp;tr=udp%3A%2F%2Fopen.demonii.com%3A1337&amp;tr=udp%3A%2F%2Ftracker.coppersurfer.tk%3A6969&amp;tr=udp%3A%2F%2Fexodus.desync.com%3A6969","seeders":0,"leechers":0,"uploader":"drunkbob","files":3,"time":1330773919,"description":"\nRest Stop (2006)(IPOD)\nEncoded to 480 x 256\nworks on IPOD/IPHONE/IPAD/MAC &amp; PC Also I watched it Via Apple TV.\n\nThe film follows Nicole Carrow, a young woman who is threatened \nby a maniac serial killer, after her boyfriend Jess, is abducted \nin a rest stop.\n\n[url]http://www.imdb.com/title/tt0787505/[/url]\n\nplease seed :P ","torrent":{"xt":"urn:btih:9aa8a5a8ed8e6c75244d93e9a84af5f8f41971e4","amp;dn":"Rest+Stop+%282006%29%28IPOD%29","amp;tr":["udp%3A%2F%2Ftracker.openbittorrent.com%3A80","udp%3A%2F%2Fopen.demonii.com%3A1337","udp%3A%2F%2Ftracker.coppersurfer.tk%3A6969","udp%3A%2F%2Fexodus.desync.com%3A6969"],"infoHash":"9aa8a5a8ed8e6c75244d93e9a84af5f8f41971e4","infoHashBuffer":{"type":"Buffer","data":[154,168,165,168,237,142,108,117,36,77,147,233,168,74,245,248,244,25,113,228]},"announce":[],"urlList":[]}}