{"title":"Sweet and Nasty Teens 5 (DvdRip)","uid":7115797,"size":1460148224,"categoryP":"porn","categoryS":"movies","magnet":"?xt=urn:btih:9f3816c41b71850a69ba33a43f34528901324f6b&amp;dn=Sweet+and+Nasty+Teens+5+%28DvdRip%29&amp;tr=udp%3A%2F%2Ftracker.openbittorrent.com%3A80&amp;tr=udp%3A%2F%2Fopen.demonii.com%3A1337&amp;tr=udp%3A%2F%2Ftracker.coppersurfer.tk%3A6969&amp;tr=udp%3A%2F%2Fexodus.desync.com%3A6969","seeders":0,"leechers":1,"uploader":"FluxXxu","files":2,"time":1332209726,"description":"Sweet and Nasty Teens 5 (DvdRip)\n\nTags: Sex, xXx, Hardcore\n\nScreens:\n &lt;a href=&quot;\nhttp://imgunix.com/viewer.php?file=8w38rmj9.jpg&quot; rel=&quot;nofollow&quot; target=&quot;_NEW&quot;&gt;\nhttp://imgunix.com/viewer.php?file=8w38rmj9.jpg&lt;/a&gt;\n &lt;a href=&quot;\nhttp://imgunix.com/viewer.php?file=2okk00mf.jpg&quot; rel=&quot;nofollow&quot; target=&quot;_NEW&quot;&gt;\nhttp://imgunix.com/viewer.php?file=2okk00mf.jpg&lt;/a&gt;\n &lt;a href=&quot;\nhttp://imgunix.com/viewer.php?file=eehki3ye.jpg&quot; rel=&quot;nofollow&quot; target=&quot;_NEW&quot;&gt;\nhttp://imgunix.com/viewer.php?file=eehki3ye.jpg&lt;/a&gt;","torrent":{"xt":"urn:btih:9f3816c41b71850a69ba33a43f34528901324f6b","amp;dn":"Sweet+and+Nasty+Teens+5+%28DvdRip%29","amp;tr":["udp%3A%2F%2Ftracker.openbittorrent.com%3A80","udp%3A%2F%2Fopen.demonii.com%3A1337","udp%3A%2F%2Ftracker.coppersurfer.tk%3A6969","udp%3A%2F%2Fexodus.desync.com%3A6969"],"infoHash":"9f3816c41b71850a69ba33a43f34528901324f6b","infoHashBuffer":{"type":"Buffer","data":[159,56,22,196,27,113,133,10,105,186,51,164,63,52,82,137,1,50,79,107]},"announce":[],"urlList":[]}}