{"title":"Android 4.0.4 Crespo (Nexus S) Full OTA Update","uid":7142267,"size":163449876,"categoryP":"applications","categoryS":"android","magnet":"?xt=urn:btih:a58a9068b38ea176f6c5ebd87b01e0494e94182b&amp;dn=Android+4.0.4+Crespo+%28Nexus+S%29+Full+OTA+Update&amp;tr=udp%3A%2F%2Ftracker.openbittorrent.com%3A80&amp;tr=udp%3A%2F%2Fopen.demonii.com%3A1337&amp;tr=udp%3A%2F%2Ftracker.coppersurfer.tk%3A6969&amp;tr=udp%3A%2F%2Fexodus.desync.com%3A6969","seeders":0,"leechers":1,"uploader":"mudvayne1993","files":1,"time":1333040430,"description":" &lt;a href=&quot;http://forum.xda-developers.com/showthread.php?t=1569509&quot; rel=&quot;nofollow&quot; target=&quot;_NEW&quot;&gt;http://forum.xda-developers.com/showthread.php?t=1569509&lt;/a&gt;\n\nOnly for Nexus S!!!!!","torrent":{"xt":"urn:btih:a58a9068b38ea176f6c5ebd87b01e0494e94182b","amp;dn":"Android+4.0.4+Crespo+%28Nexus+S%29+Full+OTA+Update","amp;tr":["udp%3A%2F%2Ftracker.openbittorrent.com%3A80","udp%3A%2F%2Fopen.demonii.com%3A1337","udp%3A%2F%2Ftracker.coppersurfer.tk%3A6969","udp%3A%2F%2Fexodus.desync.com%3A6969"],"infoHash":"a58a9068b38ea176f6c5ebd87b01e0494e94182b","infoHashBuffer":{"type":"Buffer","data":[165,138,144,104,179,142,161,118,246,197,235,216,123,1,224,73,78,148,24,43]},"announce":[],"urlList":[]}}