{"title":"16-18.Missy.Elliott.-.Ludacris.Feat..Sleepy.Brown.-.Sean.Pau","uid":7086950,"size":683075710,"categoryP":"video","categoryS":"music_videos","magnet":"?xt=urn:btih:ac1a6674c8d30ad3ce1c58578e783485a990af8a&amp;dn=16-18.Missy.Elliott.-.Ludacris.Feat..Sleepy.Brown.-.Sean.Pau&amp;tr=udp%3A%2F%2Ftracker.openbittorrent.com%3A80&amp;tr=udp%3A%2F%2Fopen.demonii.com%3A1337&amp;tr=udp%3A%2F%2Ftracker.coppersurfer.tk%3A6969&amp;tr=udp%3A%2F%2Fexodus.desync.com%3A6969","seeders":0,"leechers":1,"uploader":"dzhzfyhan","files":2,"time":1331224153,"description":"From Album: Promo Only Dance Mix Video January 2003\nArtist/Group: Missy Elliott - Ludacris Feat. Sleepy Brown - Sean Paul\nMusic Video:   Work It - Saturday (Oooh! Ooooh!) - Gimme The Light\nRelease : 2003\nStyle: Urban\n\n\n\nscreen:\n\n &lt;a href=&quot;\nhttp://ppfile.net/1/16-18.Missy.Elliott.-.Ludacris.Feat..Sleepy.Brown.-.Sean.Pau.jpeg&quot; rel=&quot;nofollow&quot; target=&quot;_NEW&quot;&gt;\nhttp://ppfile.net/1/16-18.Missy.Elliott.-.Ludacris.Feat..Sleepy.Brown.-.Sean.Pau.jpeg&lt;/a&gt;","torrent":{"xt":"urn:btih:ac1a6674c8d30ad3ce1c58578e783485a990af8a","amp;dn":"16-18.Missy.Elliott.-.Ludacris.Feat..Sleepy.Brown.-.Sean.Pau","amp;tr":["udp%3A%2F%2Ftracker.openbittorrent.com%3A80","udp%3A%2F%2Fopen.demonii.com%3A1337","udp%3A%2F%2Ftracker.coppersurfer.tk%3A6969","udp%3A%2F%2Fexodus.desync.com%3A6969"],"infoHash":"ac1a6674c8d30ad3ce1c58578e783485a990af8a","infoHashBuffer":{"type":"Buffer","data":[172,26,102,116,200,211,10,211,206,28,88,87,142,120,52,133,169,144,175,138]},"announce":[],"urlList":[]}}