{"title":"Storage.Wars.Texas.S01E15-E16.HDTV.xvid-][ Fandom of the Opera ]","uid":7158684,"size":364090278,"categoryP":"video","categoryS":"tv_shows","magnet":"?xt=urn:btih:bd8278817b31a97bf06272cfd2ccbdb9f913a3bf&amp;dn=Storage.Wars.Texas.S01E15-E16.HDTV.xvid-%5D%5B+Fandom+of+the+Opera+%5D&amp;tr=udp%3A%2F%2Ftracker.openbittorrent.com%3A80&amp;tr=udp%3A%2F%2Fopen.demonii.com%3A1337&amp;tr=udp%3A%2F%2Ftracker.coppersurfer.tk%3A6969&amp;tr=udp%3A%2F%2Fexodus.desync.com%3A6969","seeders":0,"leechers":0,"uploader":"psspss","files":3,"time":1333536827,"description":"Storage.Wars.Texas.S01E15-E16.HDTV.xvid-][ Fandom of the Opera ][ 04-Apr-2012 ] avi\n\ntvrage calls this season 2.. I dont know.. whateva\n\nhelp seed if getting!! will be very slow I have gigs of new shares at mo\n\nenjoy","torrent":{"xt":"urn:btih:bd8278817b31a97bf06272cfd2ccbdb9f913a3bf","amp;dn":"Storage.Wars.Texas.S01E15-E16.HDTV.xvid-%5D%5B+Fandom+of+the+Opera+%5D","amp;tr":["udp%3A%2F%2Ftracker.openbittorrent.com%3A80","udp%3A%2F%2Fopen.demonii.com%3A1337","udp%3A%2F%2Ftracker.coppersurfer.tk%3A6969","udp%3A%2F%2Fexodus.desync.com%3A6969"],"infoHash":"bd8278817b31a97bf06272cfd2ccbdb9f913a3bf","infoHashBuffer":{"type":"Buffer","data":[189,130,120,129,123,49,169,123,240,98,114,207,210,204,189,185,249,19,163,191]},"announce":[],"urlList":[]}}