{"title":"18OnlyGirls - Together All The Time - Melanie B. And Stephanie [","uid":7207007,"size":1058733737,"categoryP":"porn","categoryS":"hd___movies","magnet":"?xt=urn:btih:c0e7fd5c442995f75dfeacdbed12089cf4fc4509&amp;dn=18OnlyGirls+-+Together+All+The+Time+-+Melanie+B.+And+Stephanie+%5B&amp;tr=udp%3A%2F%2Ftracker.openbittorrent.com%3A80&amp;tr=udp%3A%2F%2Fopen.demonii.com%3A1337&amp;tr=udp%3A%2F%2Ftracker.coppersurfer.tk%3A6969&amp;tr=udp%3A%2F%2Fexodus.desync.com%3A6969","seeders":0,"leechers":1,"uploader":"C3Porno","files":-1,"time":1335128547,"description":"18OnlyGirls - Together All The Time - Melanie B. And Stephanie [1080p].wmv\n\n2012, Teen, Lesbian, Hardcore, HD, XXX, Adult\n\n1920 x 1080\n\n00:23:02\n\n1009.69 MB\n\nScreens\n &lt;a href=&quot;\nhttp://www.euro-pic.eu/share-BAFC_4F945487.html&quot; rel=&quot;nofollow&quot; target=&quot;_NEW&quot;&gt;\nhttp://www.euro-pic.eu/share-BAFC_4F945487.html&lt;/a&gt;\n &lt;a href=&quot;\nhttp://www.euro-pic.eu/share-7B60_4F945487.html&quot; rel=&quot;nofollow&quot; target=&quot;_NEW&quot;&gt;\nhttp://www.euro-pic.eu/share-7B60_4F945487.html&lt;/a&gt;\n &lt;a href=&quot;\nhttp://www.euro-pic.eu/share-9AA2_4F945487.html&quot; rel=&quot;nofollow&quot; target=&quot;_NEW&quot;&gt;\nhttp://www.euro-pic.eu/share-9AA2_4F945487.html&lt;/a&gt;\n &lt;a href=&quot;\nhttp://www.euro-pic.eu/share-BBE4_4F945487.html&quot; rel=&quot;nofollow&quot; target=&quot;_NEW&quot;&gt;\nhttp://www.euro-pic.eu/share-BBE4_4F945487.html&lt;/a&gt;\n &lt;a href=&quot;\nhttp://www.euro-pic.eu/share-592B_4F945487.html&quot; rel=&quot;nofollow&quot; target=&quot;_NEW&quot;&gt;\nhttp://www.euro-pic.eu/share-592B_4F945487.html&lt;/a&gt;\n &lt;a href=&quot;\nhttp://www.euro-pic.eu/share-052D_4F945487.html&quot; rel=&quot;nofollow&quot; target=&quot;_NEW&quot;&gt;\nhttp://www.euro-pic.eu/share-052D_4F945487.html&lt;/a&gt;","torrent":{"xt":"urn:btih:c0e7fd5c442995f75dfeacdbed12089cf4fc4509","amp;dn":"18OnlyGirls+-+Together+All+The+Time+-+Melanie+B.+And+Stephanie+%5B","amp;tr":["udp%3A%2F%2Ftracker.openbittorrent.com%3A80","udp%3A%2F%2Fopen.demonii.com%3A1337","udp%3A%2F%2Ftracker.coppersurfer.tk%3A6969","udp%3A%2F%2Fexodus.desync.com%3A6969"],"infoHash":"c0e7fd5c442995f75dfeacdbed12089cf4fc4509","infoHashBuffer":{"type":"Buffer","data":[192,231,253,92,68,41,149,247,93,254,172,219,237,18,8,156,244,252,69,9]},"announce":[],"urlList":[]}}