{"title":"Akta.Manniskor.S01E06.SWEDiSH.WEBRiP.XviD-Moskito","uid":7046384,"size":576822580,"categoryP":"video","categoryS":"tv_shows","magnet":"?xt=urn:btih:cec96f4a3700d41abc0450dce51ac0c61e1c8ea6&amp;dn=Akta.Manniskor.S01E06.SWEDiSH.WEBRiP.XviD-Moskito&amp;tr=udp%3A%2F%2Ftracker.openbittorrent.com%3A80&amp;tr=udp%3A%2F%2Fopen.demonii.com%3A1337&amp;tr=udp%3A%2F%2Ftracker.coppersurfer.tk%3A6969&amp;tr=udp%3A%2F%2Fexodus.desync.com%3A6969","seeders":0,"leechers":4,"uploader":"Moskitotorrents","files":-1,"time":1329758359,"description":"Svensk dramaserie frÃƒÂ¥n 2012. Avsnitt 6 av 10. Leo ÃƒÂ¤r svag men gÃƒÂ¶r allt fÃƒÂ¶r att orka ta sig ÃƒÂ¤nda fram till Mimis hus dÃƒÂ¤r Matilda ÃƒÂ¤r nÃƒÂ¥got pÃƒÂ¥ spÃƒÂ¥ren vad gÃƒÂ¤ller Anita, eller vad heter hon egentligen? NÃƒÂ¤r Bea kommer blÃƒÂ¥slagen till Rogers jobb lyckas hon lura honom fÃƒÂ¶r att fÃƒÂ¥ det hon behÃƒÂ¶ver. Lennart erbjuds gÃƒÂ¶ra en hubotkopia av sig sjÃƒÂ¤lv. Men vill man det?\n\nI rollerna: Andreas Wilson, Eva RÃƒÂ¶se, Leif AndrÃƒÂ©e, Lisette Pagler, Sten ElfstrÃƒÂ¶m, Marie Robertson.\n\nRippat och Uppladdat av Moskito fÃƒÂ¶r www.dreamseed.nu - Kvalitet framfÃƒÂ¶r kvantitet","torrent":{"xt":"urn:btih:cec96f4a3700d41abc0450dce51ac0c61e1c8ea6","amp;dn":"Akta.Manniskor.S01E06.SWEDiSH.WEBRiP.XviD-Moskito","amp;tr":["udp%3A%2F%2Ftracker.openbittorrent.com%3A80","udp%3A%2F%2Fopen.demonii.com%3A1337","udp%3A%2F%2Ftracker.coppersurfer.tk%3A6969","udp%3A%2F%2Fexodus.desync.com%3A6969"],"infoHash":"cec96f4a3700d41abc0450dce51ac0c61e1c8ea6","infoHashBuffer":{"type":"Buffer","data":[206,201,111,74,55,0,212,26,188,4,80,220,229,26,192,198,30,28,142,166]},"announce":[],"urlList":[]}}