{"title":"NBA.2012.Reg.S.(07 march).LA.Lakers.vs.WAS.Wizards.720p","uid":7086185,"size":2533002431,"categoryP":"video","categoryS":"hd___tv_shows","magnet":"?xt=urn:btih:e1485f088daacdfaf6e2d7e98daeb89a342f3af8&amp;dn=NBA.2012.Reg.S.%2807+march%29.LA.Lakers.vs.WAS.Wizards.720p&amp;tr=udp%3A%2F%2Ftracker.openbittorrent.com%3A80&amp;tr=udp%3A%2F%2Fopen.demonii.com%3A1337&amp;tr=udp%3A%2F%2Ftracker.coppersurfer.tk%3A6969&amp;tr=udp%3A%2F%2Fexodus.desync.com%3A6969","seeders":0,"leechers":1,"uploader":"Nepotu","files":4,"time":1331197192,"description":"NBA 2012 Regular Season - 07 march\n\n\nLOS ANGELES Lakers (23-15) - WASHINGTON Wizards (8-29)\n\n\nLOS ANGELES Lakers (23-15): 9. Matt Barnes, 5. Steve Blake, 24. Kobe Bryant, 17. Andrew Bynum, 3. Devin Ebanks, 2. Derek Fisher, 16. Pau Gasol, 0. Andrew Goudelock, 28. Jason Kapono, 6. Josh McRoberts, 1. Darius Morris, 14. Troy Murphy, 4. Luke Walton, 15. Metta World Peace, Coach: Mike Brown\n\n\nVideo: H264 720p\n\nCredit: Reborn4HD","torrent":{"xt":"urn:btih:e1485f088daacdfaf6e2d7e98daeb89a342f3af8","amp;dn":"NBA.2012.Reg.S.%2807+march%29.LA.Lakers.vs.WAS.Wizards.720p","amp;tr":["udp%3A%2F%2Ftracker.openbittorrent.com%3A80","udp%3A%2F%2Fopen.demonii.com%3A1337","udp%3A%2F%2Ftracker.coppersurfer.tk%3A6969","udp%3A%2F%2Fexodus.desync.com%3A6969"],"infoHash":"e1485f088daacdfaf6e2d7e98daeb89a342f3af8","infoHashBuffer":{"type":"Buffer","data":[225,72,95,8,141,170,205,250,246,226,215,233,141,174,184,154,52,47,58,248]},"announce":[],"urlList":[]}}