{"title":"jayashali","uid":7261653,"size":738276380,"categoryP":"video","categoryS":"other","magnet":"?xt=urn:btih:e52734e0c19fbffd54d64034f5e5628d79e52ab4&amp;dn=jayashali&amp;tr=udp%3A%2F%2Ftracker.openbittorrent.com%3A80&amp;tr=udp%3A%2F%2Fopen.demonii.com%3A1337&amp;tr=udp%3A%2F%2Ftracker.coppersurfer.tk%3A6969&amp;tr=udp%3A%2F%2Fexodus.desync.com%3A6969","seeders":0,"leechers":0,"uploader":"jayashali","files":1,"time":1336749139,"description":"jayashali","torrent":{"xt":"urn:btih:e52734e0c19fbffd54d64034f5e5628d79e52ab4","amp;dn":"jayashali","amp;tr":["udp%3A%2F%2Ftracker.openbittorrent.com%3A80","udp%3A%2F%2Fopen.demonii.com%3A1337","udp%3A%2F%2Ftracker.coppersurfer.tk%3A6969","udp%3A%2F%2Fexodus.desync.com%3A6969"],"infoHash":"e52734e0c19fbffd54d64034f5e5628d79e52ab4","infoHashBuffer":{"type":"Buffer","data":[229,39,52,224,193,159,191,253,84,214,64,52,245,229,98,141,121,229,42,180]},"announce":[],"urlList":[]}}