{"title":"[LoveYourTits] Sara Stone","uid":7079382,"size":387417882,"categoryP":"porn","categoryS":"movies","magnet":"?xt=urn:btih:e81a96950e8d6e3916007f4d9a5cdd3731dae5b6&amp;dn=%5BLoveYourTits%5D+Sara+Stone&amp;tr=udp%3A%2F%2Ftracker.openbittorrent.com%3A80&amp;tr=udp%3A%2F%2Fopen.demonii.com%3A1337&amp;tr=udp%3A%2F%2Ftracker.coppersurfer.tk%3A6969&amp;tr=udp%3A%2F%2Fexodus.desync.com%3A6969","seeders":0,"leechers":0,"uploader":"exmnova","files":1,"time":1330970258,"description":"[LoveYourTits] Sara Stone\n &lt;a href=&quot;\nhttp://0.picswan.com/show.php/36134_2.jpg.html&quot; rel=&quot;nofollow&quot; target=&quot;_NEW&quot;&gt;\nhttp://0.picswan.com/show.php/36134_2.jpg.html&lt;/a&gt;\n &lt;a href=&quot;\nhttp://0.picswan.com/show.php/36133_1.jpg.html&quot; rel=&quot;nofollow&quot; target=&quot;_NEW&quot;&gt;\nhttp://0.picswan.com/show.php/36133_1.jpg.html&lt;/a&gt;\n","torrent":{"xt":"urn:btih:e81a96950e8d6e3916007f4d9a5cdd3731dae5b6","amp;dn":"%5BLoveYourTits%5D+Sara+Stone","amp;tr":["udp%3A%2F%2Ftracker.openbittorrent.com%3A80","udp%3A%2F%2Fopen.demonii.com%3A1337","udp%3A%2F%2Ftracker.coppersurfer.tk%3A6969","udp%3A%2F%2Fexodus.desync.com%3A6969"],"infoHash":"e81a96950e8d6e3916007f4d9a5cdd3731dae5b6","infoHashBuffer":{"type":"Buffer","data":[232,26,150,149,14,141,110,57,22,0,127,77,154,92,221,55,49,218,229,182]},"announce":[],"urlList":[]}}