{"title":"[IKnowThatGirl] Gabriella Roxxx (Hang Up That Phone / 11.01.2012","uid":7143950,"size":292037081,"categoryP":"porn","categoryS":"movies","magnet":"?xt=urn:btih:f01a1c41c30de15e10a95f257bd7ca3cab98489b&amp;dn=%5BIKnowThatGirl%5D+Gabriella+Roxxx+%28Hang+Up+That+Phone+%2F+11.01.2012&amp;tr=udp%3A%2F%2Ftracker.openbittorrent.com%3A80&amp;tr=udp%3A%2F%2Fopen.demonii.com%3A1337&amp;tr=udp%3A%2F%2Ftracker.coppersurfer.tk%3A6969&amp;tr=udp%3A%2F%2Fexodus.desync.com%3A6969","seeders":0,"leechers":1,"uploader":"chkm8te","files":1,"time":1333091980,"description":"Screens: &lt;a href=&quot;\nhttp://4ufrom.me/viewer.php?file=nonvzt0wcpou83a9v8mo.jpg&quot; rel=&quot;nofollow&quot; target=&quot;_NEW&quot;&gt;\nhttp://4ufrom.me/viewer.php?file=nonvzt0wcpou83a9v8mo.jpg&lt;/a&gt;","torrent":{"xt":"urn:btih:f01a1c41c30de15e10a95f257bd7ca3cab98489b","amp;dn":"%5BIKnowThatGirl%5D+Gabriella+Roxxx+%28Hang+Up+That+Phone+%2F+11.01.2012","amp;tr":["udp%3A%2F%2Ftracker.openbittorrent.com%3A80","udp%3A%2F%2Fopen.demonii.com%3A1337","udp%3A%2F%2Ftracker.coppersurfer.tk%3A6969","udp%3A%2F%2Fexodus.desync.com%3A6969"],"infoHash":"f01a1c41c30de15e10a95f257bd7ca3cab98489b","infoHashBuffer":{"type":"Buffer","data":[240,26,28,65,195,13,225,94,16,169,95,37,123,215,202,60,171,152,72,155]},"announce":[],"urlList":[]}}