{"title":"Big Titty Time (2012) DVDRip","uid":7074107,"size":1461878784,"categoryP":"porn","categoryS":"movies","magnet":"?xt=urn:btih:f5392ba25cf7167903309b14af4c3f46c4508d27&amp;dn=Big+Titty+Time+%282012%29+DVDRip&amp;tr=udp%3A%2F%2Ftracker.openbittorrent.com%3A80&amp;tr=udp%3A%2F%2Fopen.demonii.com%3A1337&amp;tr=udp%3A%2F%2Ftracker.coppersurfer.tk%3A6969&amp;tr=udp%3A%2F%2Fexodus.desync.com%3A6969","seeders":0,"leechers":0,"uploader":null,"files":1,"time":1330773733,"description":" &lt;a href=&quot;http://sharezones.biz/view.php?filename=2012/03/03/image_4f51ca19a8367.jpg&quot; rel=&quot;nofollow&quot; target=&quot;_NEW&quot;&gt;http://sharezones.biz/view.php?filename=2012/03/03/image_4f51ca19a8367.jpg&lt;/a&gt;\n\n\nCast: Lisa Ann, Amy Ried, Sophie Dee, Jenna Presley, Bridgette B\n\n\n It's time for some big titty action from Jules Jordan Studios, with all of your favorite big titty broads getting banged out analy!","torrent":{"xt":"urn:btih:f5392ba25cf7167903309b14af4c3f46c4508d27","amp;dn":"Big+Titty+Time+%282012%29+DVDRip","amp;tr":["udp%3A%2F%2Ftracker.openbittorrent.com%3A80","udp%3A%2F%2Fopen.demonii.com%3A1337","udp%3A%2F%2Ftracker.coppersurfer.tk%3A6969","udp%3A%2F%2Fexodus.desync.com%3A6969"],"infoHash":"f5392ba25cf7167903309b14af4c3f46c4508d27","infoHashBuffer":{"type":"Buffer","data":[245,57,43,162,92,247,22,121,3,48,155,20,175,76,63,70,196,80,141,39]},"announce":[],"urlList":[]}}