{"title":"Judge.Judy.2012.04.14.Classic.2008.PDTV.tellymad.avi","uid":7189430,"size":198099056,"categoryP":"video","categoryS":"tv_shows","magnet":"?xt=urn:btih:fcee56a32436157d2e024037a64d25e947c1e6b8&amp;dn=Judge.Judy.2012.04.14.Classic.2008.PDTV.tellymad.avi&amp;tr=udp%3A%2F%2Ftracker.openbittorrent.com%3A80&amp;tr=udp%3A%2F%2Fopen.demonii.com%3A1337&amp;tr=udp%3A%2F%2Ftracker.coppersurfer.tk%3A6969&amp;tr=udp%3A%2F%2Fexodus.desync.com%3A6969","seeders":0,"leechers":1,"uploader":"mdprosser","files":1,"time":1334571256,"description":"Judge.Judy.2012.04.14.Classic.2008.PDTV.tellymad","torrent":{"xt":"urn:btih:fcee56a32436157d2e024037a64d25e947c1e6b8","amp;dn":"Judge.Judy.2012.04.14.Classic.2008.PDTV.tellymad.avi","amp;tr":["udp%3A%2F%2Ftracker.openbittorrent.com%3A80","udp%3A%2F%2Fopen.demonii.com%3A1337","udp%3A%2F%2Ftracker.coppersurfer.tk%3A6969","udp%3A%2F%2Fexodus.desync.com%3A6969"],"infoHash":"fcee56a32436157d2e024037a64d25e947c1e6b8","infoHashBuffer":{"type":"Buffer","data":[252,238,86,163,36,54,21,125,46,2,64,55,166,77,37,233,71,193,230,184]},"announce":[],"urlList":[]}}